injectark/__init__.py
injectark/builder.py
injectark/factory.py
injectark/injectark.py
injectark-0.7.2.dist-info/LICENSE
injectark-0.7.2.dist-info/WHEEL
injectark-0.7.2.dist-info/METADATA
injectark-0.7.2.dist-info/RECORD
