Metadata-Version: 2.1
Name: injectark
Version: 0.7.2
Summary: Dependency Injector for Python
License: MIT
Author: eecheverry
Author-email: eecheverry@nubark.com
Requires-Python: >=3.6,<4.0
Classifier: License :: OSI Approved :: MIT License
Classifier: Programming Language :: Python :: 3
Classifier: Programming Language :: Python :: 3.6
Classifier: Programming Language :: Python :: 3.7
Classifier: Programming Language :: Python :: 3.8
Classifier: Programming Language :: Python :: 3.9
